harmonixpy/__init__.py
harmonixpy/__main__.py
harmonixpy/flask_app.py
harmonixpy/test.py
HarmonixPy-0.0.5.dist-info/LICENSE
HarmonixPy-0.0.5.dist-info/METADATA
HarmonixPy-0.0.5.dist-info/WHEEL
HarmonixPy-0.0.5.dist-info/entry_points.txt
HarmonixPy-0.0.5.dist-info/top_level.txt
HarmonixPy-0.0.5.dist-info/RECORD
