Metadata-Version: 2.1
Name: HarmonixPy
Version: 0.0.5
Summary: A simple module for serving HTML and managing dependencies with Flask.
Home-page: https://github.com/d-inspiration/HarmonixPy
Author: Taripretei Zidein
Author-email: inspirante01@gmail.com
Classifier: Programming Language :: Python :: 3
Classifier: License :: OSI Approved :: Apache Software License
Classifier: Operating System :: OS Independent
Requires-Python: >=3.6
License-File: LICENSE
Requires-Dist: flask
